[{"id":"imp-1784625326453-889313","filename":null,"url":null,"previewDataUrl":null,"takenAt":null,"lat":null,"lon":null,"dateSource":"none","hash":"8915c8d642a1d3bb695e1d93430d13d11e3e23872b977304171a4965caf33810","fileSize":1247317,"duplicateNote":"The exact same file is already attached to an event in this trip.","duplicateOfUrl":"https://raw.githubusercontent.com/aponsin/roadtrip-planner/main/media/import-1784620605268-3cea6d.jpg","status":"duplicate","matches":[]},{"id":"imp-1784625326453-40a222","filename":null,"url":null,"previewDataUrl":null,"takenAt":null,"lat":null,"lon":null,"dateSource":"none","hash":"3f769d6cac6260dac26c107b246e24a477c89c6a929f1158cb0958ae76db0c3c","fileSize":1274566,"duplicateNote":"The exact same file is already attached to an event in this trip.","duplicateOfUrl":"https://raw.githubusercontent.com/aponsin/roadtrip-planner/main/media/import-1784620607920-c86888.jpg","status":"duplicate","matches":[]},{"id":"imp-1784625326454-39c529","filename":null,"url":null,"previewDataUrl":null,"takenAt":null,"lat":null,"lon":null,"dateSource":"none","hash":"99ae2cda1b3a7e562548a5b18c38a7d24588e4116e378a2086e93bc9efb128d4","fileSize":1505578,"duplicateNote":"The exact same file is already attached to an event in this trip.","duplicateOfUrl":"https://raw.githubusercontent.com/aponsin/roadtrip-planner/main/media/import-1784617790742-adb49a.jpg","status":"duplicate","matches":[]},{"id":"imp-1784625326454-be1c27","filename":null,"url":null,"previewDataUrl":null,"takenAt":null,"lat":null,"lon":null,"dateSource":"none","hash":"6ef137dc3f6f8da8baaf191086a96644b110fcf33b6f228fd354c86942c793f9","fileSize":1403100,"duplicateNote":"The exact same file is already attached to an event in this trip.","duplicateOfUrl":"https://raw.githubusercontent.com/aponsin/roadtrip-planner/main/media/import-1784623266582-8a3fce.jpg","status":"duplicate","matches":[]},{"id":"imp-1784625326454-3a117b","filename":null,"url":null,"previewDataUrl":null,"takenAt":null,"lat":null,"lon":null,"dateSource":"none","hash":"32a8c10831b9657ef25eeeefee87b3d6b0fb3be69b81d64a22084b1f59ab84c4","fileSize":895216,"duplicateNote":"The exact same file is already attached to an event in this trip.","duplicateOfUrl":"https://raw.githubusercontent.com/aponsin/roadtrip-planner/main/media/import-1784620614784-79b9d4.jpg","status":"duplicate","matches":[]},{"id":"imp-1784625326454-99592d","filename":null,"url":null,"previewDataUrl":null,"takenAt":null,"lat":null,"lon":null,"dateSource":"none","hash":"2e3c83b1a25fef94bdc26b4e91ba5cc8b4237495a2a8e84c658d3931e6386552","fileSize":1191582,"duplicateNote":"The exact same file is already attached to an event in this trip.","duplicateOfUrl":"https://raw.githubusercontent.com/aponsin/roadtrip-planner/main/media/import-1784622006851-51f08c.jpg","status":"duplicate","matches":[]},{"id":"imp-1784625326454-e12456","filename":"import-1784625327344-9c32b1.jpg","url":"https://raw.githubusercontent.com/aponsin/roadtrip-planner/main/media/_import_staging/Alaska_actual/import-1784625327344-9c32b1.jpg","previewDataUrl":null,"takenAt":1784611530000,"lat":null,"lon":null,"dateSource":"exif","hash":"3dedea693e6649e5124963e7a3675135f00d079d4acf22a7891375c533d51bed","fileSize":5155988,"duplicateNote":null,"duplicateOfUrl":null,"status":"unmatched","matches":[{"eventId":320,"score":0.192},{"eventId":330,"score":0.192},{"eventId":332,"score":0.192}],"exifNote":null},{"id":"imp-1784625326454-02e4ee","filename":null,"url":null,"previewDataUrl":null,"takenAt":null,"lat":null,"lon":null,"dateSource":"none","hash":"b687b59f7816f007230797c657bf5546efba269b34d9c4b1dd48c1298814388a","fileSize":4961940,"duplicateNote":"The exact same file is already attached to an event in this trip.","duplicateOfUrl":"https://raw.githubusercontent.com/aponsin/roadtrip-planner/main/media/import-1784620624275-cc16ed.jpg","status":"duplicate","matches":[]},{"id":"imp-1784625326454-c569c7","filename":null,"url":null,"previewDataUrl":null,"takenAt":null,"lat":null,"lon":null,"dateSource":"none","hash":"e702b2e0028d1ddce885d64b8e62333daa57ca3169fe5856be6f389cffeba57d","fileSize":4951078,"duplicateNote":"The exact same file is already attached to an event in this trip.","duplicateOfUrl":"https://raw.githubusercontent.com/aponsin/roadtrip-planner/main/media/import-1784620627762-cbaf83.jpg","status":"duplicate","matches":[]},{"id":"imp-1784625326454-6620af","filename":null,"url":null,"previewDataUrl":null,"takenAt":null,"lat":null,"lon":null,"dateSource":"none","hash":"90e1682bd191be5362955f52e83516853cfbf4fb310c0467ec7c9345c26f8e88","fileSize":9902196,"duplicateNote":"The exact same file is already attached to an event in this trip.","duplicateOfUrl":"https://raw.githubusercontent.com/aponsin/roadtrip-planner/main/media/import-1784620631406-dc8cc2.jpg","status":"duplicate","matches":[]},{"id":"imp-1784625326454-2d70f7","filename":null,"url":null,"previewDataUrl":null,"takenAt":null,"lat":null,"lon":null,"dateSource":"none","hash":"1c61e6a232be66b8d8d14f014d29498c031fd8340a814105daf262cd24e0f3d4","fileSize":9871624,"duplicateNote":"The exact same file is already attached to an event in this trip.","duplicateOfUrl":"https://raw.githubusercontent.com/aponsin/roadtrip-planner/main/media/evphoto-1784616739609-65ab54.jpg","status":"duplicate","matches":[]},{"id":"imp-1784625326454-f68d7b","filename":null,"url":null,"previewDataUrl":null,"takenAt":null,"lat":null,"lon":null,"dateSource":"none","hash":"c656cd86977272914fcf41ecc62ea60cbc8f97c31573d73e68501cf06acdff8c","fileSize":11003728,"duplicateNote":"The exact same file is already attached to an event in this trip.","duplicateOfUrl":"https://raw.githubusercontent.com/aponsin/roadtrip-planner/main/media/evphoto-1784616742408-59e7e6.jpg","status":"duplicate","matches":[]},{"id":"imp-1784625326454-13d3db","filename":null,"url":null,"previewDataUrl":null,"takenAt":null,"lat":null,"lon":null,"dateSource":"none","hash":"5baf77da91979f2c22e70e9202a91e92385434d6dc75e4ce5e0ff072830eadd9","fileSize":10952925,"duplicateNote":"The exact same file is already attached to an event in this trip.","duplicateOfUrl":"https://raw.githubusercontent.com/aponsin/roadtrip-planner/main/media/import-1784622013628-f837fc.jpg","status":"duplicate","matches":[]},{"id":"imp-1784625326454-5f797a","filename":"import-1784625331445-173c67.jpg","url":"https://raw.githubusercontent.com/aponsin/roadtrip-planner/main/media/_import_staging/Alaska_actual/import-1784625331445-173c67.jpg","previewDataUrl":null,"takenAt":1784603237000,"lat":null,"lon":null,"dateSource":"exif","hash":"267e5aab692317b54c704a5375f40a753143b932f2ef1208a44bec19b979b303","fileSize":6058860,"duplicateNote":null,"duplicateOfUrl":null,"status":"unmatched","matches":[{"eventId":320,"score":0.192},{"eventId":330,"score":0.192},{"eventId":332,"score":0.192}],"exifNote":null},{"id":"imp-1784625326454-e530fb","filename":"import-1784625334383-9e24cf.jpg","url":"https://raw.githubusercontent.com/aponsin/roadtrip-planner/main/media/_import_staging/Alaska_actual/import-1784625334383-9e24cf.jpg","previewDataUrl":null,"takenAt":1784599207000,"lat":null,"lon":null,"dateSource":"exif","hash":"2333c9c75fe9794749e74828f9b1b40ffff8e2b659be78f01ea326817ee03771","fileSize":4029434,"duplicateNote":null,"duplicateOfUrl":null,"status":"unmatched","matches":[{"eventId":320,"score":0.192},{"eventId":330,"score":0.192},{"eventId":332,"score":0.192}],"exifNote":null},{"id":"imp-1784625326454-e0201c","filename":"import-1784625337337-6bb267.jpg","url":"https://raw.githubusercontent.com/aponsin/roadtrip-planner/main/media/_import_staging/Alaska_actual/import-1784625337337-6bb267.jpg","previewDataUrl":null,"takenAt":1784599196000,"lat":null,"lon":null,"dateSource":"exif","hash":"0464c01139bc9748655420cf0c979a4bf7e601ebf229ac3df15a9e11a136e320","fileSize":3721388,"duplicateNote":null,"duplicateOfUrl":null,"status":"unmatched","matches":[{"eventId":320,"score":0.192},{"eventId":330,"score":0.192},{"eventId":332,"score":0.192}],"exifNote":null},{"id":"imp-1784625326454-cc0539","filename":"import-1784625341516-0ec8dc.jpg","url":"https://raw.githubusercontent.com/aponsin/roadtrip-planner/main/media/_import_staging/Alaska_actual/import-1784625341516-0ec8dc.jpg","previewDataUrl":null,"takenAt":1784599192000,"lat":null,"lon":null,"dateSource":"exif","hash":"95732588e03fdfc3b1aba10bcbde39fa33913496a204f39a9d26daac1baa9ec4","fileSize":3435102,"duplicateNote":null,"duplicateOfUrl":null,"status":"unmatched","matches":[{"eventId":320,"score":0.192},{"eventId":330,"score":0.192},{"eventId":332,"score":0.192}],"exifNote":null},{"id":"imp-1784625326454-54a603","filename":"import-1784625344302-730c42.jpg","url":"https://raw.githubusercontent.com/aponsin/roadtrip-planner/main/media/_import_staging/Alaska_actual/import-1784625344302-730c42.jpg","previewDataUrl":null,"takenAt":1784598884000,"lat":null,"lon":null,"dateSource":"exif","hash":"f1ab52f7709abb3fc466df148ffe3f7d3b7d3aa6b95234760bb6070efe399706","fileSize":2407625,"duplicateNote":null,"duplicateOfUrl":null,"status":"unmatched","matches":[{"eventId":320,"score":0.192},{"eventId":330,"score":0.192},{"eventId":332,"score":0.192}],"exifNote":null},{"id":"imp-1784625326455-4d6efa","filename":"import-1784625346848-406dd5.jpg","url":"https://raw.githubusercontent.com/aponsin/roadtrip-planner/main/media/_import_staging/Alaska_actual/import-1784625346848-406dd5.jpg","previewDataUrl":null,"takenAt":1784598881000,"lat":null,"lon":null,"dateSource":"exif","hash":"3203ff3396316b7fd98ebf043cfd21184742c4e49242015d71680b0a86e791d6","fileSize":2132151,"duplicateNote":null,"duplicateOfUrl":null,"status":"unmatched","matches":[{"eventId":320,"score":0.192},{"eventId":330,"score":0.192},{"eventId":332,"score":0.192}],"exifNote":null},{"id":"imp-1784625326455-f5e1f2","filename":"import-1784625349727-9a668f.jpg","url":"https://raw.githubusercontent.com/aponsin/roadtrip-planner/main/media/_import_staging/Alaska_actual/import-1784625349727-9a668f.jpg","previewDataUrl":null,"takenAt":1784597268000,"lat":null,"lon":null,"dateSource":"exif","hash":"021e3767557a22f4467f7dabe247331e563786c0cab325bdcb76698ee96107bf","fileSize":2271837,"duplicateNote":null,"duplicateOfUrl":null,"status":"unmatched","matches":[{"eventId":320,"score":0.192},{"eventId":330,"score":0.192},{"eventId":332,"score":0.192}],"exifNote":null},{"id":"imp-1784625326455-acfaf9","filename":"import-1784625353103-455b70.jpg","url":null,"previewDataUrl":null,"takenAt":1784597257000,"lat":null,"lon":null,"dateSource":"exif","hash":"892759757ff30023757e11b9f8320ae41544d9662a12b539f1771931fdd82f91","fileSize":1655250,"duplicateNote":null,"duplicateOfUrl":null,"status":"processing","matches":[],"exifNote":null},{"id":"imp-1784625326455-311420","filename":null,"url":null,"previewDataUrl":null,"takenAt":null,"lat":null,"lon":null,"dateSource":"none","hash":null,"fileSize":1233482,"duplicateNote":null,"duplicateOfUrl":null,"status":"processing","matches":[]},{"id":"imp-1784625326455-8e4b9c","filename":null,"url":null,"previewDataUrl":null,"takenAt":null,"lat":null,"lon":null,"dateSource":"none","hash":null,"fileSize":1973052,"duplicateNote":null,"duplicateOfUrl":null,"status":"processing","matches":[]},{"id":"imp-1784625326455-61d77b","filename":null,"url":null,"previewDataUrl":null,"takenAt":null,"lat":null,"lon":null,"dateSource":"none","hash":null,"fileSize":2149147,"duplicateNote":null,"duplicateOfUrl":null,"status":"processing","matches":[]},{"id":"imp-1784625326455-f28ffa","filename":null,"url":null,"previewDataUrl":null,"takenAt":null,"lat":null,"lon":null,"dateSource":"none","hash":null,"fileSize":2610345,"duplicateNote":null,"duplicateOfUrl":null,"status":"processing","matches":[]},{"id":"imp-1784625326455-7b2dfc","filename":null,"url":null,"previewDataUrl":null,"takenAt":null,"lat":null,"lon":null,"dateSource":"none","hash":null,"fileSize":4510099,"duplicateNote":null,"duplicateOfUrl":null,"status":"processing","matches":[]},{"id":"imp-1784625326455-1c8176","filename":null,"url":null,"previewDataUrl":null,"takenAt":null,"lat":null,"lon":null,"dateSource":"none","hash":null,"fileSize":4694676,"duplicateNote":null,"duplicateOfUrl":null,"status":"processing","matches":[]},{"id":"imp-1784625326455-3206a9","filename":null,"url":null,"previewDataUrl":null,"takenAt":null,"lat":null,"lon":null,"dateSource":"none","hash":null,"fileSize":4137552,"duplicateNote":null,"duplicateOfUrl":null,"status":"processing","matches":[]},{"id":"imp-1784625326455-6ba2d7","filename":null,"url":null,"previewDataUrl":null,"takenAt":null,"lat":null,"lon":null,"dateSource":"none","hash":null,"fileSize":3619122,"duplicateNote":null,"duplicateOfUrl":null,"status":"processing","matches":[]},{"id":"imp-1784625326455-4ddc1e","filename":null,"url":null,"previewDataUrl":null,"takenAt":null,"lat":null,"lon":null,"dateSource":"none","hash":null,"fileSize":2484557,"duplicateNote":null,"duplicateOfUrl":null,"status":"processing","matches":[]},{"id":"imp-1784625326455-6bb368","filename":null,"url":null,"previewDataUrl":null,"takenAt":null,"lat":null,"lon":null,"dateSource":"none","hash":null,"fileSize":2426947,"duplicateNote":null,"duplicateOfUrl":null,"status":"processing","matches":[]},{"id":"imp-1784625326455-41fbed","filename":null,"url":null,"previewDataUrl":null,"takenAt":null,"lat":null,"lon":null,"dateSource":"none","hash":null,"fileSize":5676690,"duplicateNote":null,"duplicateOfUrl":null,"status":"processing","matches":[]},{"id":"imp-1784625326455-275b53","filename":null,"url":null,"previewDataUrl":null,"takenAt":null,"lat":null,"lon":null,"dateSource":"none","hash":null,"fileSize":6657754,"duplicateNote":null,"duplicateOfUrl":null,"status":"processing","matches":[]},{"id":"imp-1784625326455-b878d0","filename":null,"url":null,"previewDataUrl":null,"takenAt":null,"lat":null,"lon":null,"dateSource":"none","hash":null,"fileSize":5842135,"duplicateNote":null,"duplicateOfUrl":null,"status":"processing","matches":[]},{"id":"imp-1784625326455-36b81d","filename":null,"url":null,"previewDataUrl":null,"takenAt":null,"lat":null,"lon":null,"dateSource":"none","hash":null,"fileSize":1590378,"duplicateNote":null,"duplicateOfUrl":null,"status":"processing","matches":[]},{"id":"imp-1784625326455-96d70f","filename":null,"url":null,"previewDataUrl":null,"takenAt":null,"lat":null,"lon":null,"dateSource":"none","hash":null,"fileSize":12462816,"duplicateNote":null,"duplicateOfUrl":null,"status":"processing","matches":[]},{"id":"imp-1784625326456-e5bf28","filename":null,"url":null,"previewDataUrl":null,"takenAt":null,"lat":null,"lon":null,"dateSource":"none","hash":null,"fileSize":10637417,"duplicateNote":null,"duplicateOfUrl":null,"status":"processing","matches":[]},{"id":"imp-1784625326456-c1811a","filename":null,"url":null,"previewDataUrl":null,"takenAt":null,"lat":null,"lon":null,"dateSource":"none","hash":null,"fileSize":4035945,"duplicateNote":null,"duplicateOfUrl":null,"status":"processing","matches":[]},{"id":"imp-1784625326456-a364b3","filename":null,"url":null,"previewDataUrl":null,"takenAt":null,"lat":null,"lon":null,"dateSource":"none","hash":null,"fileSize":3898016,"duplicateNote":null,"duplicateOfUrl":null,"status":"processing","matches":[]},{"id":"imp-1784625326456-1fc885","filename":null,"url":null,"previewDataUrl":null,"takenAt":null,"lat":null,"lon":null,"dateSource":"none","hash":null,"fileSize":4881931,"duplicateNote":null,"duplicateOfUrl":null,"status":"processing","matches":[]},{"id":"imp-1784625326456-e45db1","filename":null,"url":null,"previewDataUrl":null,"takenAt":null,"lat":null,"lon":null,"dateSource":"none","hash":null,"fileSize":3876087,"duplicateNote":null,"duplicateOfUrl":null,"status":"processing","matches":[]},{"id":"imp-1784625326456-ed8915","filename":null,"url":null,"previewDataUrl":null,"takenAt":null,"lat":null,"lon":null,"dateSource":"none","hash":null,"fileSize":3104361,"duplicateNote":null,"duplicateOfUrl":null,"status":"processing","matches":[]},{"id":"imp-1784625326456-3de449","filename":null,"url":null,"previewDataUrl":null,"takenAt":null,"lat":null,"lon":null,"dateSource":"none","hash":null,"fileSize":1358294,"duplicateNote":null,"duplicateOfUrl":null,"status":"processing","matches":[]},{"id":"imp-1784625326456-a57225","filename":null,"url":null,"previewDataUrl":null,"takenAt":null,"lat":null,"lon":null,"dateSource":"none","hash":null,"fileSize":966589,"duplicateNote":null,"duplicateOfUrl":null,"status":"processing","matches":[]},{"id":"imp-1784625326456-e4c7b4","filename":null,"url":null,"previewDataUrl":null,"takenAt":null,"lat":null,"lon":null,"dateSource":"none","hash":null,"fileSize":1729666,"duplicateNote":null,"duplicateOfUrl":null,"status":"processing","matches":[]},{"id":"imp-1784625326456-73c86d","filename":null,"url":null,"previewDataUrl":null,"takenAt":null,"lat":null,"lon":null,"dateSource":"none","hash":null,"fileSize":1083592,"duplicateNote":null,"duplicateOfUrl":null,"status":"processing","matches":[]},{"id":"imp-1784625326456-375352","filename":null,"url":null,"previewDataUrl":null,"takenAt":null,"lat":null,"lon":null,"dateSource":"none","hash":null,"fileSize":1813843,"duplicateNote":null,"duplicateOfUrl":null,"status":"processing","matches":[]},{"id":"imp-1784625326456-ad4ad5","filename":null,"url":null,"previewDataUrl":null,"takenAt":null,"lat":null,"lon":null,"dateSource":"none","hash":null,"fileSize":131539,"duplicateNote":null,"duplicateOfUrl":null,"status":"processing","matches":[]},{"id":"imp-1784625326456-bea86c","filename":null,"url":null,"previewDataUrl":null,"takenAt":null,"lat":null,"lon":null,"dateSource":"none","hash":null,"fileSize":76219,"duplicateNote":null,"duplicateOfUrl":null,"status":"processing","matches":[]},{"id":"imp-1784625326456-6be4ef","filename":null,"url":null,"previewDataUrl":null,"takenAt":null,"lat":null,"lon":null,"dateSource":"none","hash":null,"fileSize":1747259,"duplicateNote":null,"duplicateOfUrl":null,"status":"processing","matches":[]}]